{
    "category": {
        "roles": [
            "Robotgruppen",
            "3D-skrivarcertifierad"
        ]
},
    "channels": [
        {
            "name": "游녦v칛lkommen",
            "topic": "V칛lkommen! V칛lj ditt lag s친 f친r du tillg친ng till resterande kanaler.\n\nWelcome! Select your team and you will have access to the remaining channels."
        },
        {
            "name": "游닉info",
            "topic": "H칛r finner ni viktig information s친som datum och regler.\n\nHere you will find important information like dates and rules."
        }
    ]
}